fur/__init__.py
fur-1.0.1.dist-info/METADATA
fur-1.0.1.dist-info/WHEEL
fur-1.0.1.dist-info/licenses/LICENSE.txt
fur-1.0.1.dist-info/RECORD
