Metadata-Version: 2.3
Name: fur
Version: 1.0.1
Summary: A very soft python package.
Author: Mitchell Medeiros
License-Expression: MIT
License-File: LICENSE.txt
Classifier: Intended Audience :: Developers
Classifier: License :: OSI Approved :: MIT License
Classifier: Operating System :: MacOS
Classifier: Operating System :: Microsoft :: Windows
Classifier: Operating System :: POSIX :: Linux
Classifier: Operating System :: Unix
Classifier: Programming Language :: Python
Classifier: Programming Language :: Python :: 3
Classifier: Programming Language :: Python :: 3 :: Only
Classifier: Programming Language :: Python :: 3.10
Classifier: Programming Language :: Python :: 3.11
Classifier: Programming Language :: Python :: 3.12
Classifier: Programming Language :: Python :: Implementation :: CPython
Classifier: Typing :: Typed
Requires-Python: >=3.10
Provides-Extra: dev
Requires-Dist: black>=24.0.0; extra == 'dev'
Requires-Dist: ipykernel>=6.0.0; extra == 'dev'
Requires-Dist: pytest-cov>=5.0.0; extra == 'dev'
Requires-Dist: pytest>=8.0.0; extra == 'dev'
Requires-Dist: ruff>=0.5.0; extra == 'dev'
Provides-Extra: docs
Requires-Dist: matplotlib>=3.9.1; extra == 'docs'
Requires-Dist: pydata-sphinx-theme==0.15.4; extra == 'docs'
Requires-Dist: python-dotenv==1.0.1; extra == 'docs'
Requires-Dist: sphinx-autodoc-typehints==2.2.3; extra == 'docs'
Requires-Dist: sphinx-copybutton==0.5.2; extra == 'docs'
Requires-Dist: sphinx-design==0.6.0; extra == 'docs'
Requires-Dist: sphinx-docsearch==0.0.7; extra == 'docs'
Requires-Dist: sphinx-sitemap==2.6.0; extra == 'docs'
Requires-Dist: sphinx==7.3.7; extra == 'docs'
Requires-Dist: sphinxext-opengraph==0.9.1; extra == 'docs'
